{
  "name": "Destroyed",
  "type": "wrapper",
  "_id": "mcFmBEgb646JRBbz",
  "img": "systems/teriock/src/icons/properties/destroyed.webp",
  "system": {
    "proficient": false,
    "fluent": false,
    "font": "",
    "description": "<p>None.</p>",
    "disabled": false,
    "updateCounter": true,
    "onUse": []
  },
  "effects": [
    {
      "name": "Destroyed",
      "type": "property",
      "img": "systems/teriock/src/icons/properties/destroyed.webp",
      "system": {
        "proficient": false,
        "fluent": false,
        "font": "",
        "description": "<p><span class=\"property-box\">An item that's Destroyed has been reduced to dust and can not be repaired through any known means.</span>\n</p>",
        "deleteOnExpire": false,
        "updateCounter": false,
        "suppression": {
          "statuses": {
            "active": [],
            "inactive": []
          },
          "comparisons": {
            "actor": [],
            "item": []
          }
        },
        "wikiNamespace": "Property",
        "form": "intrinsic",
        "damageType": ""
      },
      "_id": "TFYFy8GqPq9VR6oK",
      "changes": [],
      "disabled": false,
      "duration": {
        "startTime": null,
        "combat": null
      },
      "description": "<p><span class=\"property-box\">An item that's Destroyed has been reduced to dust and can not be repaired through any known means.</span>\n</p>",
      "origin": null,
      "tint": "#ffffff",
      "transfer": true,
      "statuses": [],
      "sort": 0,
      "flags": {},
      "_stats": {
        "compendiumSource": null,
        "duplicateSource": null,
        "exportSource": null,
        "coreVersion": "13.345",
        "systemId": "teriock",
        "systemVersion": "0.1.0",
        "createdTime": 1756341209225,
        "modifiedTime": 1756341209672,
        "lastModifiedBy": "qf5JYGZKzM588nE6"
      },
      "_key": "!items.effects!mcFmBEgb646JRBbz.TFYFy8GqPq9VR6oK"
    }
  ],
  "folder": null,
  "sort": 0,
  "ownership": {
    "default": 0,
    "qf5JYGZKzM588nE6": 3
  },
  "flags": {},
  "_stats": {
    "compendiumSource": null,
    "duplicateSource": null,
    "exportSource": null,
    "coreVersion": "13.345",
    "systemId": "teriock",
    "systemVersion": "0.1.0",
    "createdTime": 1756341209175,
    "modifiedTime": 1756341209709,
    "lastModifiedBy": "qf5JYGZKzM588nE6"
  },
  "_key": "!items!mcFmBEgb646JRBbz"
}
