{
  "name": "Master Crafted Runic Silver Throwing Axe",
  "type": "equipment",
  "folder": "UfmU7rRoVfOb68F9",
  "system": {
    "htmlFields": [
      "description",
      "flaws",
      "specialRules",
      "notes"
    ],
    "equipmentType": "Throwing Axe",
    "tier": {
      "raw": "",
      "derived": 0
    },
    "proficient": false,
    "fluent": false,
    "font": "",
    "description": "<p>None.</p>",
    "disabled": false,
    "updateCounter": true,
    "wikiNamespace": "Equipment",
    "equipped": true,
    "glued": false,
    "shattered": false,
    "dampened": false,
    "consumable": false,
    "quantity": 1,
    "maxQuantity": {
      "raw": "",
      "derived": 0
    },
    "ranged": false,
    "damage": "1d4",
    "twoHandedDamage": "1d6",
    "damageTypes": [],
    "weight": 2,
    "range": 60,
    "shortRange": 20,
    "equipmentClasses": [
      "impactWeapons"
    ],
    "minStr": -3,
    "sb": "gladiator",
    "av": 0,
    "bv": 1,
    "specialRules": "Throwing axes gain <span class=\"sb\" data-val=\"Gladiator\"><span class=\"property-box style-box\"> <a href=\"https://wiki.teriock.com/index.php/Core:Style_Bonus\" title=\"Core:Style Bonus\" target=\"_blank\">SB</a> when you're <a href=\"https://wiki.teriock.com/index.php/Category:Attack_abilities\" title=\"Category:Attack abilities\" target=\"_blank\">attacking</a> a <a href=\"https://wiki.teriock.com/index.php/Condition:Prone\" title=\"Condition:Prone\" target=\"_blank\">prone</a>, <a href=\"https://wiki.teriock.com/index.php/Condition:Snared\" title=\"Condition:Snared\" target=\"_blank\">snared</a>, <a href=\"https://wiki.teriock.com/index.php/Condition:Frightened\" title=\"Condition:Frightened\" target=\"_blank\">frightened</a>, or <a href=\"https://wiki.teriock.com/index.php/Condition:Hacked\" title=\"Condition:Hacked\" target=\"_blank\">hacked</a> creature.</span></span>",
    "powerLevel": "mundane",
    "flaws": "",
    "notes": "",
    "identified": true,
    "reference": null
  },
  "_id": "Wa07AY1uKHZuOqtQ",
  "img": "systems/teriock/assets/equipment/throwing-axe.svg",
  "effects": [
    {
      "name": "Versatile",
      "type": "property",
      "img": "systems/teriock/assets/property.svg",
      "system": {
        "htmlFields": [
          "description"
        ],
        "propertyType": "intrinsic",
        "description": "<p><span class=\"property-box\">A weapon with the Versatile property can be used in one or two hands. The two-handed damage value appears in parentheses next to the one-handed value.</span>\n</p>",
        "proficient": false,
        "fluent": false,
        "font": "",
        "deleteOnExpire": false,
        "updateCounter": false,
        "wikiNamespace": "Property",
        "damageType": ""
      },
      "_id": "rSnxyGNhMQaHQvfC",
      "changes": [],
      "disabled": false,
      "duration": {
        "startTime": null,
        "combat": null
      },
      "description": "",
      "origin": null,
      "tint": "#ffffff",
      "transfer": true,
      "statuses": [],
      "sort": 0,
      "flags": {},
      "_stats": {
        "compendiumSource": null,
        "duplicateSource": null,
        "exportSource": null,
        "coreVersion": "13.345",
        "systemId": "teriock",
        "systemVersion": "0.1.0",
        "createdTime": 1753136661050,
        "modifiedTime": 1753136661050,
        "lastModifiedBy": "IIjfAJm5Tf1B6G7t"
      },
      "_key": "!items.effects!Wa07AY1uKHZuOqtQ.rSnxyGNhMQaHQvfC"
    },
    {
      "name": "Weapon",
      "type": "property",
      "img": "systems/teriock/assets/property.svg",
      "system": {
        "htmlFields": [
          "description"
        ],
        "propertyType": "intrinsic",
        "description": "<p><span class=\"property-box\">A <b>weapon</b> is an item that can be used to <a href=\"https://wiki.teriock.com/index.php/Category:Attack_abilities\" title=\"Category:Attack abilities\" target=\"_blank\">attack</a>.</span>\n</p>",
        "proficient": false,
        "fluent": false,
        "font": "",
        "deleteOnExpire": false,
        "updateCounter": false,
        "wikiNamespace": "Property",
        "damageType": ""
      },
      "_id": "y6J5e59q2fanXz5I",
      "changes": [],
      "disabled": false,
      "duration": {
        "startTime": null,
        "combat": null
      },
      "description": "",
      "origin": null,
      "tint": "#ffffff",
      "transfer": true,
      "statuses": [],
      "sort": 0,
      "flags": {},
      "_stats": {
        "compendiumSource": null,
        "duplicateSource": null,
        "exportSource": null,
        "coreVersion": "13.345",
        "systemId": "teriock",
        "systemVersion": "0.1.0",
        "createdTime": 1753136661077,
        "modifiedTime": 1753136661077,
        "lastModifiedBy": "IIjfAJm5Tf1B6G7t"
      },
      "_key": "!items.effects!Wa07AY1uKHZuOqtQ.y6J5e59q2fanXz5I"
    },
    {
      "name": "AP",
      "type": "property",
      "img": "systems/teriock/assets/property.svg",
      "system": {
        "htmlFields": [
          "description"
        ],
        "propertyType": "intrinsic",
        "description": "<p><span class=\"property-box\">An item with this property is <a href=\"https://wiki.teriock.com/index.php/Property:AV0\" title=\"Property:AV0\" target=\"_blank\">AV0</a> when wielded in two hands.</span>\n</p>",
        "proficient": false,
        "fluent": false,
        "font": "",
        "deleteOnExpire": false,
        "updateCounter": false,
        "wikiNamespace": "Property",
        "damageType": ""
      },
      "_id": "BjSICF7cjXjwIufv",
      "changes": [],
      "disabled": false,
      "duration": {
        "startTime": null,
        "combat": null
      },
      "description": "",
      "origin": null,
      "tint": "#ffffff",
      "transfer": true,
      "statuses": [],
      "sort": 0,
      "flags": {},
      "_stats": {
        "compendiumSource": null,
        "duplicateSource": null,
        "exportSource": null,
        "coreVersion": "13.345",
        "systemId": "teriock",
        "systemVersion": "0.1.0",
        "createdTime": 1753136661104,
        "modifiedTime": 1753136661104,
        "lastModifiedBy": "IIjfAJm5Tf1B6G7t"
      },
      "_key": "!items.effects!Wa07AY1uKHZuOqtQ.BjSICF7cjXjwIufv"
    },
    {
      "name": "Master Crafted",
      "type": "property",
      "img": "systems/teriock/assets/property.svg",
      "system": {
        "htmlFields": [
          "description"
        ],
        "propertyType": "intrinsic",
        "description": "<p><span class=\"property-box\">Master Crafted items can be enchanted. Although this is not a <a href=\"https://wiki.teriock.com/index.php/Category:Magical_properties\" title=\"Category:Magical properties\" target=\"_blank\">magical property</a>, Master Crafted items cannot be crafted unless their maker has an ability that explicitly lets them do so.</span>\n</p>",
        "proficient": false,
        "fluent": false,
        "font": "",
        "deleteOnExpire": false,
        "updateCounter": false,
        "wikiNamespace": "Property",
        "damageType": ""
      },
      "_id": "RdwRQI8gmVliHvtB",
      "changes": [],
      "disabled": false,
      "duration": {
        "startTime": null,
        "combat": null
      },
      "description": "",
      "origin": null,
      "tint": "#ffffff",
      "transfer": true,
      "statuses": [],
      "sort": 0,
      "flags": {},
      "_stats": {
        "compendiumSource": null,
        "duplicateSource": null,
        "exportSource": null,
        "coreVersion": "13.345",
        "systemId": "teriock",
        "systemVersion": "0.1.0",
        "createdTime": 1753136661152,
        "modifiedTime": 1753136661152,
        "lastModifiedBy": "IIjfAJm5Tf1B6G7t"
      },
      "_key": "!items.effects!Wa07AY1uKHZuOqtQ.RdwRQI8gmVliHvtB"
    },
    {
      "name": "Runic",
      "type": "property",
      "img": "systems/teriock/assets/property.svg",
      "system": {
        "htmlFields": [
          "description"
        ],
        "propertyType": "normal",
        "description": "<p><span class=\"property-box\"><b>Runic</b> items repair themselves. If a runic item is also <a href=\"https://wiki.teriock.com/index.php/Property:Shattered\" title=\"Property:Shattered\" target=\"_blank\">shattered</a>, it retains the runic property. When a creature is <a href=\"https://wiki.teriock.com/index.php/Core:Attunement\" class=\"mw-redirect\" title=\"Core:Attunement\" target=\"_blank\">attuned</a> to a <a href=\"https://wiki.teriock.com/index.php/Property:Shattered\" title=\"Property:Shattered\" target=\"_blank\">shattered</a> runic item, they roll <span class=\"dice\" data-full-roll=\"2d4\" data-quick-roll=\"@2d4\"><a target=\"_blank\" rel=\"nofollow noreferrer noopener\" class=\"external text\" href=\"https://dice.run/#/d/2d4\">2d4</a></span> at the end of each of their turns. If at least 1 die rolls a 4, the item is no longer <a href=\"https://wiki.teriock.com/index.php/Property:Shattered\" title=\"Property:Shattered\" target=\"_blank\">shattered</a>.</span>\n</p>",
        "proficient": false,
        "fluent": false,
        "font": "",
        "deleteOnExpire": false,
        "updateCounter": false,
        "wikiNamespace": "Property",
        "damageType": ""
      },
      "_id": "9bVsoNasXyolAdws",
      "changes": [],
      "disabled": false,
      "duration": {
        "startTime": null,
        "combat": null
      },
      "description": "",
      "origin": null,
      "tint": "#ffffff",
      "transfer": true,
      "statuses": [],
      "sort": 0,
      "flags": {},
      "_stats": {
        "compendiumSource": null,
        "duplicateSource": null,
        "exportSource": null,
        "coreVersion": "13.345",
        "systemId": "teriock",
        "systemVersion": "0.1.0",
        "createdTime": 1753136661212,
        "modifiedTime": 1753136661212,
        "lastModifiedBy": "IIjfAJm5Tf1B6G7t"
      },
      "_key": "!items.effects!Wa07AY1uKHZuOqtQ.9bVsoNasXyolAdws"
    },
    {
      "name": "Silver",
      "type": "property",
      "img": "systems/teriock/assets/property.svg",
      "system": {
        "htmlFields": [
          "description"
        ],
        "propertyType": "intrinsic",
        "description": "<p><span class=\"property-box\">Items that are Silver can <a href=\"https://wiki.teriock.com/index.php/Core:Block_Interaction\" title=\"Core:Block Interaction\" target=\"_blank\">block</a> <a href=\"https://wiki.teriock.com/index.php/Drain:Mana\" title=\"Drain:Mana\" target=\"_blank\">mana draining</a> <a href=\"https://wiki.teriock.com/index.php/Category:Attack_abilities\" title=\"Category:Attack abilities\" target=\"_blank\">attacks</a> even if they are <a href=\"https://wiki.teriock.com/index.php/Keyword:UB\" title=\"Keyword:UB\" target=\"_blank\">UB</a>. If you are wearing Silver <a href=\"https://wiki.teriock.com/index.php/Category:Armor\" title=\"Category:Armor\" target=\"_blank\">armor</a>, then <a href=\"https://wiki.teriock.com/index.php/Drain:Mana\" title=\"Drain:Mana\" target=\"_blank\">mana draining</a> <a href=\"https://wiki.teriock.com/index.php/Category:Attack_abilities\" title=\"Category:Attack abilities\" target=\"_blank\">attacks</a> made against you are not <a href=\"https://wiki.teriock.com/index.php/Keyword:AV0\" title=\"Keyword:AV0\" target=\"_blank\">AV0</a>. Silver items also deal <a href=\"https://wiki.teriock.com/index.php/Damage:Silver\" title=\"Damage:Silver\" target=\"_blank\">silver damage</a>.</span>\n</p>",
        "proficient": false,
        "fluent": false,
        "font": "",
        "deleteOnExpire": false,
        "updateCounter": false,
        "wikiNamespace": "Property",
        "damageType": ""
      },
      "_id": "IW2FKaQZ6bIVov83",
      "changes": [],
      "disabled": false,
      "duration": {
        "startTime": null,
        "combat": null
      },
      "description": "",
      "origin": null,
      "tint": "#ffffff",
      "transfer": true,
      "statuses": [],
      "sort": 0,
      "flags": {},
      "_stats": {
        "compendiumSource": null,
        "duplicateSource": null,
        "exportSource": null,
        "coreVersion": "13.345",
        "systemId": "teriock",
        "systemVersion": "0.1.0",
        "createdTime": 1753136661239,
        "modifiedTime": 1753136661239,
        "lastModifiedBy": "IIjfAJm5Tf1B6G7t"
      },
      "_key": "!items.effects!Wa07AY1uKHZuOqtQ.IW2FKaQZ6bIVov83"
    }
  ],
  "sort": 0,
  "ownership": {
    "default": 0,
    "IIjfAJm5Tf1B6G7t": 3
  },
  "flags": {},
  "_stats": {
    "compendiumSource": null,
    "duplicateSource": null,
    "exportSource": null,
    "coreVersion": "13.345",
    "systemId": "teriock",
    "systemVersion": "0.1.0",
    "createdTime": 1753136660953,
    "modifiedTime": 1753136661251,
    "lastModifiedBy": "IIjfAJm5Tf1B6G7t"
  },
  "_key": "!items!Wa07AY1uKHZuOqtQ"
}
