{
  "name": "Glued",
  "type": "equipment",
  "system": {
    "description": "This equipment is a wrapper for Glued.",
    "tier": {
      "raw": "",
      "derived": 0
    },
    "proficient": false,
    "fluent": false,
    "font": "",
    "disabled": false,
    "updateCounter": true,
    "onUse": [],
    "wikiNamespace": "Equipment",
    "equipped": true,
    "glued": false,
    "shattered": false,
    "dampened": false,
    "consumable": false,
    "quantity": 1,
    "maxQuantity": {
      "raw": "",
      "derived": 0
    },
    "ranged": false,
    "damage": "0",
    "twoHandedDamage": "0",
    "damageTypes": [],
    "weight": 0,
    "range": 0,
    "shortRange": 0,
    "equipmentClasses": [],
    "minStr": -3,
    "sb": null,
    "av": 0,
    "bv": 0,
    "specialRules": "",
    "equipmentType": "Equipment Type",
    "price": 0,
    "powerLevel": "mundane",
    "flaws": "",
    "notes": "",
    "identified": true,
    "reference": null
  },
  "folder": "4hVAkycExF590TKG",
  "_id": "gje9t8H2jhzcetCs",
  "img": "systems/teriock/src/icons/properties/glued.webp",
  "effects": [
    {
      "name": "Glued",
      "type": "property",
      "img": "systems/teriock/src/icons/properties/glued.webp",
      "system": {
        "proficient": false,
        "fluent": false,
        "font": "",
        "description": "<p><span class=\"property-box\">If an item is Glued to a creature, it is bound to their spirit. The item and creature are <a href=\"https://wiki.teriock.com/index.php/Keyword:Immunity\" title=\"Keyword:Immunity\" target=\"_blank\">immune</a> to <a href=\"https://wiki.teriock.com/index.php/Category:Stealing_effects\" title=\"Category:Stealing effects\" target=\"_blank\">effects that would steal it</a> from the creature's body (even if the creature is dead).\n</span></p>\n<div class=\"note\"><b>Note:</b> This does not prevent the creature from throwing, dropping, or handing off the item. In which case, the item is still Glued to them.</div>",
        "deleteOnExpire": false,
        "updateCounter": false,
        "suppression": {
          "statuses": {
            "active": [],
            "inactive": []
          },
          "comparisons": {
            "actor": [],
            "item": []
          }
        },
        "wikiNamespace": "Property",
        "form": "normal",
        "damageType": ""
      },
      "_id": "Scu2iXJ7LOc1H6UR",
      "changes": [],
      "disabled": false,
      "duration": {
        "startTime": null,
        "combat": null
      },
      "description": "<p><span class=\"property-box\">If an item is Glued to a creature, it is bound to their spirit. The item and creature are <a href=\"https://wiki.teriock.com/index.php/Keyword:Immunity\" title=\"Keyword:Immunity\" target=\"_blank\">immune</a> to <a href=\"https://wiki.teriock.com/index.php/Category:Stealing_effects\" title=\"Category:Stealing effects\" target=\"_blank\">effects that would steal it</a> from the creature's body (even if the creature is dead).\n</span></p>\n<div class=\"note\"><b>Note:</b> This does not prevent the creature from throwing, dropping, or handing off the item. In which case, the item is still Glued to them.</div>",
      "origin": null,
      "tint": "#ffffff",
      "transfer": true,
      "statuses": [],
      "sort": 0,
      "flags": {},
      "_stats": {
        "compendiumSource": null,
        "duplicateSource": null,
        "exportSource": null,
        "coreVersion": "13.345",
        "systemId": "teriock",
        "systemVersion": "0.1.0",
        "createdTime": 1754458291544,
        "modifiedTime": 1756252093780,
        "lastModifiedBy": "qf5JYGZKzM588nE6"
      },
      "_key": "!items.effects!gje9t8H2jhzcetCs.Scu2iXJ7LOc1H6UR"
    }
  ],
  "sort": 0,
  "ownership": {
    "default": 0,
    "uxE8DDp7ujgsxtd2": 3
  },
  "flags": {
    "teriock": {
      "propertyWrapper": true,
      "effectWrapper": true
    }
  },
  "_stats": {
    "compendiumSource": null,
    "duplicateSource": null,
    "exportSource": null,
    "coreVersion": "13.345",
    "systemId": "teriock",
    "systemVersion": "0.1.0",
    "createdTime": 1754458291486,
    "modifiedTime": 1756252093798,
    "lastModifiedBy": "qf5JYGZKzM588nE6"
  },
  "_key": "!items!gje9t8H2jhzcetCs"
}
