{
  "allured": {
    "_id": "allured000000000",
    "description": "<p>@Embed[Compendium.teriock.rules.JournalEntry.condition0000000.JournalEntryPage.allured000000000 inline text]</p>",
    "id": "allured",
    "img": "systems/teriock/src/icons/conditions/allured.webp",
    "name": "TERIOCK.STATUSES.Conditions.allured",
    "statuses": [
      "bound"
    ],
    "type": "condition",
    "system": {
      "identifier": "allured"
    }
  },
  "anosmatic": {
    "_id": "anosmatic0000000",
    "description": "<p>@Embed[Compendium.teriock.rules.JournalEntry.condition0000000.JournalEntryPage.anosmatic0000000 inline text]</p>",
    "id": "anosmatic",
    "img": "icons/creatures/slimes/slime-face-hollow-green.webp",
    "name": "TERIOCK.STATUSES.Conditions.anosmatic",
    "statuses": [],
    "type": "condition",
    "system": {
      "identifier": "anosmatic"
    }
  },
  "asleep": {
    "_id": "asleep0000000000",
    "description": "<p>@Embed[Compendium.teriock.rules.JournalEntry.condition0000000.JournalEntryPage.asleep0000000000 inline text]</p>",
    "id": "asleep",
    "img": "systems/teriock/src/icons/conditions/asleep.webp",
    "name": "TERIOCK.STATUSES.Conditions.asleep",
    "statuses": [
      "unconscious",
      "down",
      "blind",
      "prone"
    ],
    "type": "condition",
    "system": {
      "identifier": "asleep"
    }
  },
  "blind": {
    "_id": "blind00000000000",
    "description": "<p>@Embed[Compendium.teriock.rules.JournalEntry.condition0000000.JournalEntryPage.blind00000000000 inline text]</p>",
    "id": "blind",
    "img": "icons/creatures/eyes/humanoid-single-blind.webp",
    "name": "TERIOCK.STATUSES.Conditions.blind",
    "statuses": [],
    "type": "condition",
    "system": {
      "identifier": "blind"
    }
  },
  "bound": {
    "_id": "bound00000000000",
    "description": "<p>@Embed[Compendium.teriock.rules.JournalEntry.condition0000000.JournalEntryPage.bound00000000000 inline text]</p>",
    "id": "bound",
    "img": "systems/teriock/src/icons/conditions/bound.webp",
    "name": "TERIOCK.STATUSES.Conditions.bound",
    "statuses": [],
    "type": "condition",
    "system": {
      "identifier": "bound"
    }
  },
  "burned": {
    "_id": "burned0000000000",
    "description": "<p>@Embed[Compendium.teriock.rules.JournalEntry.condition0000000.JournalEntryPage.burned0000000000 inline text]</p>",
    "id": "burned",
    "img": "systems/teriock/src/icons/conditions/burned.webp",
    "name": "TERIOCK.STATUSES.Conditions.burned",
    "statuses": [],
    "type": "condition",
    "system": {
      "identifier": "burned"
    }
  },
  "charmed": {
    "_id": "charmed000000000",
    "description": "<p>@Embed[Compendium.teriock.rules.JournalEntry.condition0000000.JournalEntryPage.charmed000000000 inline text]</p>",
    "id": "charmed",
    "img": "systems/teriock/src/icons/conditions/charmed.webp",
    "name": "TERIOCK.STATUSES.Conditions.charmed",
    "statuses": [],
    "type": "condition",
    "system": {
      "identifier": "charmed"
    }
  },
  "criticallyWounded": {
    "_id": "criticallyWounde",
    "description": "<p>@Embed[Compendium.teriock.rules.JournalEntry.condition0000000.JournalEntryPage.criticallyWounde inline text]</p>",
    "id": "criticallyWounded",
    "img": "systems/teriock/src/icons/conditions/critically-wounded.webp",
    "name": "TERIOCK.STATUSES.Conditions.criticallyWounded",
    "statuses": [
      "down",
      "prone"
    ],
    "type": "condition",
    "system": {
      "identifier": "critically-wounded"
    }
  },
  "dead": {
    "_id": "dead000000000000",
    "description": "<p>@Embed[Compendium.teriock.rules.JournalEntry.condition0000000.JournalEntryPage.dead000000000000 inline text]</p>",
    "id": "dead",
    "img": "systems/teriock/src/icons/conditions/dead.webp",
    "name": "TERIOCK.STATUSES.Conditions.dead",
    "statuses": [
      "down",
      "prone"
    ],
    "type": "condition",
    "system": {
      "identifier": "dead"
    }
  },
  "deaf": {
    "_id": "deaf000000000000",
    "description": "<p>@Embed[Compendium.teriock.rules.JournalEntry.condition0000000.JournalEntryPage.deaf000000000000 inline text]</p>",
    "id": "deaf",
    "img": "systems/teriock/src/icons/conditions/deaf.webp",
    "name": "TERIOCK.STATUSES.Conditions.deaf",
    "statuses": [],
    "type": "condition",
    "system": {
      "identifier": "deaf"
    }
  },
  "defyingDeath": {
    "_id": "defyingDeath0000",
    "description": "<p>@Embed[Compendium.teriock.rules.JournalEntry.condition0000000.JournalEntryPage.defyingDeath0000 inline text]</p>",
    "id": "defyingDeath",
    "img": "systems/teriock/src/icons/conditions/defying-death.webp",
    "name": "TERIOCK.STATUSES.Conditions.defyingDeath",
    "statuses": [],
    "type": "condition",
    "system": {
      "identifier": "defying-death"
    }
  },
  "disguised": {
    "_id": "disguised0000000",
    "description": "<p>@Embed[Compendium.teriock.rules.JournalEntry.condition0000000.JournalEntryPage.disguised0000000 inline text]</p>",
    "id": "disguised",
    "img": "systems/teriock/src/icons/conditions/disguised.webp",
    "name": "TERIOCK.STATUSES.Conditions.disguised",
    "statuses": [],
    "type": "condition",
    "system": {
      "identifier": "disguised"
    }
  },
  "down": {
    "_id": "down000000000000",
    "description": "<p>@Embed[Compendium.teriock.rules.JournalEntry.condition0000000.JournalEntryPage.down000000000000 inline text]</p>",
    "id": "down",
    "img": "systems/teriock/src/icons/conditions/down.webp",
    "name": "TERIOCK.STATUSES.Conditions.down",
    "statuses": [],
    "type": "condition",
    "system": {
      "identifier": "down"
    }
  },
  "dueling": {
    "_id": "dueling000000000",
    "description": "<p>@Embed[Compendium.teriock.rules.JournalEntry.condition0000000.JournalEntryPage.dueling000000000 inline text]</p>",
    "id": "dueling",
    "img": "systems/teriock/src/icons/conditions/dueling.webp",
    "name": "TERIOCK.STATUSES.Conditions.dueling",
    "statuses": [],
    "type": "condition",
    "system": {
      "identifier": "dueling"
    }
  },
  "encumbered": {
    "_id": "encumbered000000",
    "description": "<p>@Embed[Compendium.teriock.rules.JournalEntry.condition0000000.JournalEntryPage.encumbered000000 inline text]</p>",
    "id": "encumbered",
    "img": "systems/teriock/src/icons/conditions/encumbered.webp",
    "name": "TERIOCK.STATUSES.Conditions.encumbered",
    "statuses": [],
    "type": "condition",
    "system": {
      "identifier": "encumbered"
    }
  },
  "ethereal": {
    "_id": "ethereal00000000",
    "description": "<p>@Embed[Compendium.teriock.rules.JournalEntry.condition0000000.JournalEntryPage.ethereal00000000 inline text]</p>",
    "id": "ethereal",
    "img": "systems/teriock/src/icons/conditions/ethereal.webp",
    "name": "TERIOCK.STATUSES.Conditions.ethereal",
    "statuses": [],
    "type": "condition",
    "system": {
      "identifier": "ethereal"
    }
  },
  "frenzied": {
    "_id": "frenzied00000000",
    "description": "<p>@Embed[Compendium.teriock.rules.JournalEntry.condition0000000.JournalEntryPage.frenzied00000000 inline text]</p>",
    "id": "frenzied",
    "img": "systems/teriock/src/icons/conditions/frenzied.webp",
    "name": "TERIOCK.STATUSES.Conditions.frenzied",
    "statuses": [],
    "type": "condition",
    "system": {
      "identifier": "frenzied"
    }
  },
  "frightened": {
    "_id": "frightened000000",
    "description": "<p>@Embed[Compendium.teriock.rules.JournalEntry.condition0000000.JournalEntryPage.frightened000000 inline text]</p>",
    "id": "frightened",
    "img": "systems/teriock/src/icons/conditions/frightened.webp",
    "name": "TERIOCK.STATUSES.Conditions.frightened",
    "statuses": [],
    "type": "condition",
    "system": {
      "identifier": "frightened"
    }
  },
  "frozen": {
    "_id": "frozen0000000000",
    "description": "<p>@Embed[Compendium.teriock.rules.JournalEntry.condition0000000.JournalEntryPage.frozen0000000000 inline text]</p>",
    "id": "frozen",
    "img": "systems/teriock/src/icons/conditions/frozen.webp",
    "name": "TERIOCK.STATUSES.Conditions.frozen",
    "statuses": [],
    "type": "condition",
    "system": {
      "identifier": "frozen"
    }
  },
  "goaded": {
    "_id": "goaded0000000000",
    "description": "<p>@Embed[Compendium.teriock.rules.JournalEntry.condition0000000.JournalEntryPage.goaded0000000000 inline text]</p>",
    "id": "goaded",
    "img": "systems/teriock/src/icons/conditions/goaded.webp",
    "name": "TERIOCK.STATUSES.Conditions.goaded",
    "statuses": [],
    "type": "condition",
    "system": {
      "identifier": "goaded"
    }
  },
  "grounded": {
    "_id": "grounded00000000",
    "description": "<p>@Embed[Compendium.teriock.rules.JournalEntry.condition0000000.JournalEntryPage.grounded00000000 inline text]</p>",
    "id": "grounded",
    "img": "systems/teriock/src/icons/conditions/grounded.webp",
    "name": "TERIOCK.STATUSES.Conditions.grounded",
    "statuses": [],
    "type": "condition",
    "system": {
      "identifier": "grounded"
    }
  },
  "hacked": {
    "_id": "hacked0000000000",
    "description": "<p>@Embed[Compendium.teriock.rules.JournalEntry.condition0000000.JournalEntryPage.hacked0000000000 inline text]</p>",
    "id": "hacked",
    "img": "systems/teriock/src/icons/conditions/hacked.webp",
    "name": "TERIOCK.STATUSES.Conditions.hacked",
    "statuses": [],
    "type": "condition",
    "system": {
      "identifier": "hacked"
    }
  },
  "hidden": {
    "_id": "hidden0000000000",
    "description": "<p>@Embed[Compendium.teriock.rules.JournalEntry.condition0000000.JournalEntryPage.hidden0000000000 inline text]</p>",
    "id": "hidden",
    "img": "systems/teriock/src/icons/conditions/hidden.webp",
    "name": "TERIOCK.STATUSES.Conditions.hidden",
    "statuses": [],
    "type": "condition",
    "system": {
      "identifier": "hidden"
    }
  },
  "hollied": {
    "_id": "hollied000000000",
    "description": "<p>@Embed[Compendium.teriock.rules.JournalEntry.condition0000000.JournalEntryPage.hollied000000000 inline text]</p>",
    "id": "hollied",
    "img": "systems/teriock/src/icons/conditions/hollied.webp",
    "name": "TERIOCK.STATUSES.Conditions.hollied",
    "statuses": [],
    "type": "condition",
    "system": {
      "identifier": "hollied"
    }
  },
  "immobilized": {
    "_id": "immobilized00000",
    "description": "<p>@Embed[Compendium.teriock.rules.JournalEntry.condition0000000.JournalEntryPage.immobilized00000 inline text]</p>",
    "id": "immobilized",
    "img": "systems/teriock/src/icons/conditions/immobilized.webp",
    "name": "TERIOCK.STATUSES.Conditions.immobilized",
    "statuses": [],
    "type": "condition",
    "system": {
      "identifier": "immobilized"
    }
  },
  "invisible": {
    "_id": "invisible0000000",
    "description": "<p>@Embed[Compendium.teriock.rules.JournalEntry.condition0000000.JournalEntryPage.invisible0000000 inline text]</p>",
    "id": "invisible",
    "img": "systems/teriock/src/icons/conditions/invisible.webp",
    "name": "TERIOCK.STATUSES.Conditions.invisible",
    "statuses": [],
    "type": "condition",
    "system": {
      "identifier": "invisible"
    }
  },
  "lighted": {
    "_id": "lighted000000000",
    "description": "<p>@Embed[Compendium.teriock.rules.JournalEntry.condition0000000.JournalEntryPage.lighted000000000 inline text]</p>",
    "id": "lighted",
    "img": "systems/teriock/src/icons/conditions/lighted.webp",
    "name": "TERIOCK.STATUSES.Conditions.lighted",
    "statuses": [],
    "type": "condition",
    "system": {
      "identifier": "lighted"
    }
  },
  "meleeDodging": {
    "_id": "meleeDodging0000",
    "description": "<p>@Embed[Compendium.teriock.rules.JournalEntry.condition0000000.JournalEntryPage.meleeDodging0000 inline text]</p>",
    "id": "meleeDodging",
    "img": "systems/teriock/src/icons/conditions/melee-dodging.webp",
    "name": "TERIOCK.STATUSES.Conditions.meleeDodging",
    "statuses": [],
    "type": "condition",
    "system": {
      "identifier": "melee-dodging"
    }
  },
  "missileDodging": {
    "_id": "missileDodging00",
    "description": "<p>@Embed[Compendium.teriock.rules.JournalEntry.condition0000000.JournalEntryPage.missileDodging00 inline text]</p>",
    "id": "missileDodging",
    "img": "systems/teriock/src/icons/conditions/missile-dodging.webp",
    "name": "TERIOCK.STATUSES.Conditions.missileDodging",
    "statuses": [],
    "type": "condition",
    "system": {
      "identifier": "missile-dodging"
    }
  },
  "mute": {
    "_id": "mute000000000000",
    "description": "<p>@Embed[Compendium.teriock.rules.JournalEntry.condition0000000.JournalEntryPage.mute000000000000 inline text]</p>",
    "id": "mute",
    "img": "systems/teriock/src/icons/conditions/mute.webp",
    "name": "TERIOCK.STATUSES.Conditions.mute",
    "statuses": [],
    "type": "condition",
    "system": {
      "identifier": "mute"
    }
  },
  "odorless": {
    "_id": "odorless00000000",
    "description": "<p>@Embed[Compendium.teriock.rules.JournalEntry.condition0000000.JournalEntryPage.odorless00000000 inline text]</p>",
    "id": "odorless",
    "img": "systems/teriock/src/icons/conditions/odorless.webp",
    "name": "TERIOCK.STATUSES.Conditions.odorless",
    "statuses": [],
    "type": "condition",
    "system": {
      "identifier": "odorless"
    }
  },
  "paralyzed": {
    "_id": "paralyzed0000000",
    "description": "<p>@Embed[Compendium.teriock.rules.JournalEntry.condition0000000.JournalEntryPage.paralyzed0000000 inline text]</p>",
    "id": "paralyzed",
    "img": "systems/teriock/src/icons/conditions/paralyzed.webp",
    "name": "TERIOCK.STATUSES.Conditions.paralyzed",
    "statuses": [
      "immobilized"
    ],
    "type": "condition",
    "system": {
      "identifier": "paralyzed"
    }
  },
  "poisoned": {
    "_id": "poisoned00000000",
    "description": "<p>@Embed[Compendium.teriock.rules.JournalEntry.condition0000000.JournalEntryPage.poisoned00000000 inline text]</p>",
    "id": "poisoned",
    "img": "systems/teriock/src/icons/conditions/poisoned.webp",
    "name": "TERIOCK.STATUSES.Conditions.poisoned",
    "statuses": [],
    "type": "condition",
    "system": {
      "identifier": "poisoned"
    }
  },
  "prone": {
    "_id": "prone00000000000",
    "description": "<p>@Embed[Compendium.teriock.rules.JournalEntry.condition0000000.JournalEntryPage.prone00000000000 inline text]</p>",
    "id": "prone",
    "img": "systems/teriock/src/icons/conditions/prone.webp",
    "name": "TERIOCK.STATUSES.Conditions.prone",
    "statuses": [],
    "type": "condition",
    "system": {
      "identifier": "prone"
    }
  },
  "ruined": {
    "_id": "ruined0000000000",
    "description": "<p>@Embed[Compendium.teriock.rules.JournalEntry.condition0000000.JournalEntryPage.ruined0000000000 inline text]</p>",
    "id": "ruined",
    "img": "systems/teriock/src/icons/conditions/ruined.webp",
    "name": "TERIOCK.STATUSES.Conditions.ruined",
    "statuses": [
      "dead",
      "down"
    ],
    "type": "condition",
    "system": {
      "identifier": "ruined"
    }
  },
  "silenced": {
    "_id": "silenced00000000",
    "description": "<p>@Embed[Compendium.teriock.rules.JournalEntry.condition0000000.JournalEntryPage.silenced00000000 inline text]</p>",
    "id": "silenced",
    "img": "systems/teriock/src/icons/conditions/silenced.webp",
    "name": "TERIOCK.STATUSES.Conditions.silenced",
    "statuses": [
      "mute"
    ],
    "type": "condition",
    "system": {
      "identifier": "silenced"
    }
  },
  "silent": {
    "_id": "silent0000000000",
    "description": "<p>@Embed[Compendium.teriock.rules.JournalEntry.condition0000000.JournalEntryPage.silent0000000000 inline text]</p>",
    "id": "silent",
    "img": "systems/teriock/src/icons/conditions/silent.webp",
    "name": "TERIOCK.STATUSES.Conditions.silent",
    "statuses": [],
    "type": "condition",
    "system": {
      "identifier": "silent"
    }
  },
  "slowed": {
    "_id": "slowed0000000000",
    "description": "<p>@Embed[Compendium.teriock.rules.JournalEntry.condition0000000.JournalEntryPage.slowed0000000000 inline text]</p>",
    "id": "slowed",
    "img": "systems/teriock/src/icons/conditions/slowed.webp",
    "name": "TERIOCK.STATUSES.Conditions.slowed",
    "statuses": [],
    "type": "condition",
    "system": {
      "identifier": "slowed"
    }
  },
  "snared": {
    "_id": "snared0000000000",
    "description": "<p>@Embed[Compendium.teriock.rules.JournalEntry.condition0000000.JournalEntryPage.snared0000000000 inline text]</p>",
    "id": "snared",
    "img": "systems/teriock/src/icons/conditions/snared.webp",
    "name": "TERIOCK.STATUSES.Conditions.snared",
    "statuses": [
      "immobilized"
    ],
    "type": "condition",
    "system": {
      "identifier": "snared"
    }
  },
  "suffocating": {
    "_id": "suffocating00000",
    "description": "<p>@Embed[Compendium.teriock.rules.JournalEntry.condition0000000.JournalEntryPage.suffocating00000 inline text]</p>",
    "id": "suffocating",
    "img": "systems/teriock/src/icons/conditions/suffocating.webp",
    "name": "TERIOCK.STATUSES.Conditions.suffocating",
    "statuses": [],
    "type": "condition",
    "system": {
      "identifier": "suffocating"
    }
  },
  "terrored": {
    "_id": "terrored00000000",
    "description": "<p>@Embed[Compendium.teriock.rules.JournalEntry.condition0000000.JournalEntryPage.terrored00000000 inline text]</p>",
    "id": "terrored",
    "img": "systems/teriock/src/icons/conditions/terrored.webp",
    "name": "TERIOCK.STATUSES.Conditions.terrored",
    "statuses": [],
    "type": "condition",
    "system": {
      "identifier": "terrored"
    }
  },
  "transformed": {
    "_id": "transformed00000",
    "description": "<p>@Embed[Compendium.teriock.rules.JournalEntry.condition0000000.JournalEntryPage.transformed00000 inline text]</p>",
    "id": "transformed",
    "img": "systems/teriock/src/icons/conditions/transformed.webp",
    "name": "TERIOCK.STATUSES.Conditions.transformed",
    "statuses": [],
    "type": "condition",
    "system": {
      "identifier": "transformed"
    }
  },
  "unconscious": {
    "_id": "unconscious00000",
    "description": "<p>@Embed[Compendium.teriock.rules.JournalEntry.condition0000000.JournalEntryPage.unconscious00000 inline text]</p>",
    "id": "unconscious",
    "img": "systems/teriock/src/icons/conditions/unconscious.webp",
    "name": "TERIOCK.STATUSES.Conditions.unconscious",
    "statuses": [
      "down",
      "prone"
    ],
    "type": "condition",
    "system": {
      "identifier": "unconscious"
    }
  },
  "wisping": {
    "_id": "wisping000000000",
    "description": "<p>@Embed[Compendium.teriock.rules.JournalEntry.condition0000000.JournalEntryPage.wisping000000000 inline text]</p>",
    "id": "wisping",
    "img": "systems/teriock/src/icons/conditions/wisping.webp",
    "name": "TERIOCK.STATUSES.Conditions.wisping",
    "statuses": [
      "ethereal"
    ],
    "type": "condition",
    "system": {
      "identifier": "wisping",
      "transformation": {
        "enabled": true,
        "level": "greater",
        "reset": [
          "hp",
          "mp",
          "gp"
        ],
        "uuids": [
          "Compendium.teriock.species.Item.cda2fe02543abcfe"
        ]
      }
    }
  }
}
