{
  "TERIOCK": {
    "STATUSES": {
      "Cover": {
        "fullCover": "Full Cover",
        "halfCover": "Half Cover",
        "noCover": "No Cover",
        "threeQuartersCover": "Three Quarters Cover"
      },
      "Hacks": {
        "armHack": "Arm Hack",
        "armHack1": "Arm Hack 1",
        "armHack2": "Arm Hack 2",
        "bodyHack": "Body Hack",
        "earHack": "Ear Hack",
        "eyeHack": "Eye Hack",
        "legHack": "Leg Hack",
        "legHack1": "Leg Hack 1",
        "legHack2": "Leg Hack 2",
        "mouthHack": "Mouth Hack",
        "noseHack": "Nose Hack"
      },
      "Transformations": {
        "fullTransformed": "Full Transformed",
        "greaterTransformed": "Greater Transformed",
        "illusionTransformed": "Illusion transformed",
        "minorTransformed": "Minor Transformed",
        "polymorphed": "Polymorphed",
        "treeformed": "Treeformed"
      }
    }
  }
}
